tryalot/__init__.py
tryalot-0.5.0.dist-info/LICENSE
tryalot-0.5.0.dist-info/METADATA
tryalot-0.5.0.dist-info/WHEEL
tryalot-0.5.0.dist-info/RECORD
