Metadata-Version: 2.1
Name: tryalot
Version: 0.5.0
Summary: Try a lot without worrying about the hassle.
Home-page: https://github.com/yuttie/tryalot
License: MIT
Author: Yuta Taniguchi
Author-email: yuta.taniguchi.y.t@gmail.com
Requires-Python: >=3.9,<4.0
Classifier: License :: OSI Approved :: MIT License
Classifier: Programming Language :: Python :: 3
Classifier: Programming Language :: Python :: 3.9
Classifier: Programming Language :: Python :: 3.10
Classifier: Programming Language :: Python :: 3.11
Classifier: Programming Language :: Python :: 3.12
Classifier: Programming Language :: Python :: 3.13
Requires-Dist: graphviz (>=0.19,<0.21)
Requires-Dist: zstandard (>=0.16.0,<0.24)
Project-URL: Repository, https://github.com/yuttie/tryalot
